{
    "interface": "DenseNetInterface",
    "dense_blocks": [
        6,
        12,
        24,
        16
    ],
    "growth_rate": 32,
    "compression_factor": 0.5,
    "n_classes": 3,
    "dropout_rate": 0.1,
    "optimizer": {
        "recipe_name": "Adam",
        "parameters": {
            "learning_rate": 0.001
        }
    },
    "loss_function": {
        "recipe_name": "FScoreLoss",
        "parameters": {}
    },
    "metrics": [
        {
            "recipe_name": "CategoricalAccuracy",
            "parameters": {}
        },
        {
            "recipe_name": "Precision",
            "parameters": {}
        },
        {
            "recipe_name": "Recall",
            "parameters": {}
        }
    ]
}
